{
    "hot": [
        {
            "headlines": [
                {
                    "title": "美国空军“从头开始”审查第六代战斗机项目",
                    "url": "https://toutiao.china.com/s_ayjr/xw/toutiao1/13000098/20240906/47174025.html?ayjr"
                }
            ],
            "list": [
                [
                    {
                        "title": "特朗普：若当选将正式成立“政府效率委员会”，由马斯克领导",
                        "url": "https://toutiao.china.com/s_ayjr/xw/toutiao1/13000098/20240906/47174026.html?ayjr"
                    }
                ],
                [
                    {
                        "title": "现代支付被执行超 515 万，原告为 POS 机厂商",
                        "url": "https://toutiao.china.com/s_ayjr/xw/toutiao1/13000098/20240906/47174027.html?ayjr"
                    }
                ]
            ]
        },
        {
            "headlines": [
                {
                    "title": "塞内加尔商人买了100辆中国新能源车：到我们国",
                    "url": "https://toutiao.china.com/s_ayjr/xw/toutiao1/13000098/20240906/47174011.html?ayjr"
                }
            ],
            "list": [
                [
                    {
                        "title": "美国在多米尼加扣押第二架与马杜罗相关飞机",
                        "url": "https://toutiao.china.com/s_ayjr/xw/toutiao1/13000098/20240906/47174012.html?ayjr"
                    },
                    {
                        "title": "外交部：中方一贯反对美国将经贸科技问题政治化",
                        "url": "https://toutiao.china.com/s_ayjr/shsy/gundong/13000120/20240906/47173219.html?ayjr"
                    }
                ]
            ]
        },
        {
            "headlines": [
                {
                    "title": "“非”常“中”！中国新能源技术在南非大放光",
                    "url": "https://toutiao.china.com/s_ayjr/shsy/gundong/13000120/20240906/47173088.html?ayjr"
                }
            ],
            "list": [
                [
                    {
                        "title": "以色列国防军称袭击黎巴嫩南部多地目标",
                        "url": "https://toutiao.china.com/s_ayjr/shsy/gundong3/13000181/20240906/47172454.html?ayjr"
                    },
                    {
                        "title": "我国自主研制的民用涡轴发动机获颁型号合格证",
                        "url": "https://toutiao.china.com/s_ayjr/shsy/gundong/13000120/20240906/47172390.html?ayjr"
                    }
                ]
            ]
        },
        {
            "headlines": [
                {
                    "title": "以军从约旦河西岸城市杰宁撤出",
                    "url": "https://toutiao.china.com/s_ayjr/shsy/gundong3/13000181/20240906/47172345.html?ayjr"
                }
            ],
            "list": [
                [
                    {
                        "title": "一中学原副校长被查，家中搜出6700万现金？南京官方回应",
                        "url": "https://toutiao.china.com/s_ayjr/xw/toutiao1/13000098/20240906/47171701.html?ayjr"
                    },
                    {
                        "title": "华为云董事长、法定代表人变更",
                        "url": "https://toutiao.china.com/s_ayjr/xw/toutiao1/13000098/20240906/47171702.html?ayjr"
                    }
                ]
            ]
        }
    ],
    "focus": [
        {
            "title": "“故意”允许儿子持枪 美校园枪击案枪手父亲被捕",
            "url": "https://toutiao.china.com/s_ayjr/shsy/gundong3/13000181/20240906/47174673.html?ayjr",
            "img": "https://img2.utuku.imgcdc.com/300x0/news/20240906/3fe90086-37cb-4a51-8bd8-3097ed7669e4.jpg"
        },
        {
            "title": "商务部回应中国在世贸组织起诉加拿大对华征税措施",
            "url": "https://toutiao.china.com/s_ayjr/shsy/gundong/13000120/20240906/47174652.html?ayjr",
            "img": "https://img1.utuku.imgcdc.com/300x0/news/20240906/34002026-2650-4bb9-bd9e-3f9899f0b088.jpg"
        }
    ],
    "smallImg": [
        {
            "title": "日媒：欧盟想从中国药厂手中夺回控制权，但前景不明",
            "url": "https://toutiao.china.com/s_ayjr/xw/toutiao1/13000098/20240906/47174018.html?ayjr",
            "img": "https://img1.utuku.imgcdc.com/360x0/toutiao/20240906/5dff77fd-b262-4390-94db-771cde0cd927.jpg"
        },
        {
            "title": "超强台风“摩羯”或成为登陆海南的最强台风",
            "url": "https://toutiao.china.com/s_ayjr/xw/toutiao1/13000098/20240906/47174019.html?ayjr",
            "img": "https://news.huawangzhixun.com/picture/2508923786739895630327/1274_1058$1.20"
        },
        {
            "title": "同组的巴林、印尼都拿分了，国足出线前景不乐观",
            "url": "https://toutiao.china.com/s_ayjr/xw/toutiao1/13000098/20240906/47174020.html?ayjr",
            "img": "https://img0.utuku.imgcdc.com/360x0/toutiao/20240906/3a9e2b4e-304b-46f0-81c1-04362be25ea9.jpg"
        },
        {
            "title": "球迷桂二牛因病逝世 当地足协、俱乐部发文悼念",
            "url": "https://toutiao.china.com/s_ayjr/xw/toutiao1/13000098/20240906/47174021.html?ayjr",
            "img": "https://news.huawangzhixun.com/picture/4164450262645244984360/628_523$1.20"
        }
    ],
    "midImg": [
        {
            "title": "中国长征六号运载火箭一箭十星发射成功",
            "url": "https://toutiao.china.com/s_ayjr/xw/toutiao1/13000098/20240906/47174014.html?ayjr",
            "img": "https://img1.utuku.imgcdc.com/360x0/toutiao/20240906/192dca06-a831-47e7-92c7-fb38f18cbb9f.jpg"
        },
        {
            "title": "五角大楼：美国认为向基辅转让远程武器的效果微乎其微",
            "url": "https://toutiao.china.com/s_ayjr/xw/toutiao1/13000098/20240906/47174015.html?ayjr",
            "img": "https://img0.utuku.imgcdc.com/360x0/toutiao/20240906/daeec487-ae2d-463e-be0f-825a731a357b.jpg"
        },
        {
            "title": "今天下午3点全岛停电？海口供电局：假的",
            "url": "https://toutiao.china.com/s_ayjr/xw/toutiao1/13000098/20240906/47174016.html?ayjr",
            "img": "https://img1.utuku.imgcdc.com/360x0/toutiao/20240906/28013116-5e4c-4569-928c-487c7938f419.jpg"
        },
        {
            "title": "新加坡高校学者：在加征关税问题上，中国认为加拿大比美国欧盟更恶劣",
            "url": "https://toutiao.china.com/s_ayjr/xw/toutiao1/13000098/20240906/47174017.html?ayjr",
            "img": "https://news.huawangzhixun.com/picture/1003729544201360175756/1024_682$1.50"
        }
    ],
    "bigImg": [
        {
            "title": "浙江省政协原副主席朱从玖受贿案一审开庭",
            "url": "https://toutiao.china.com/s_ayjr/shsy/gundong/13000120/20240906/47174640.html?ayjr",
            "img": "https://img3.utuku.imgcdc.com/300x0/news/20240906/b52be891-01ef-4f85-af70-87b34ad9e0f0.jpg"
        },
        {
            "title": "美国称加沙停火协议谈成90% 以色列否认",
            "url": "https://toutiao.china.com/s_ayjr/shsy/gundong3/13000181/20240906/47174629.html?ayjr",
            "img": "https://img2.utuku.imgcdc.com/650x0/news/20240906/4ed7bf67-4c6d-4d27-8bf7-0bfc783eb418.jpg"
        },
        {
            "title": "最大风力17级！台风“摩羯”在海南文昌沿海登陆",
            "url": "https://toutiao.china.com/s_ayjr/shsy/gundong/13000120/20240906/47174619.html?ayjr",
            "img": "https://img1.utuku.imgcdc.com/409x0/news/20240906/190ecbf1-6816-4b83-a6d7-5b712e2af4fd.jpg"
        },
        {
            "title": "中非合作论坛上，“龙墩墩”受外宾青睐",
            "url": "https://toutiao.china.com/s_ayjr/shsy/gundong/13000120/20240906/47174607.html?ayjr",
            "img": "https://img1.utuku.imgcdc.com/300x0/news/20240906/e5b61139-c6fa-4aca-9ef0-2eb4455406a1.jpg"
        }
    ],
    "imgText": [
        {
            "title": "华为云董事长、法定代表人变更",
            "url": "https://toutiao.china.com/s_ayjr/xw/toutiao1/13000098/20240906/47171702.html?ayjr"
        },
        {
            "title": "“利润挑战”，中国车企智能电动化时代必修课",
            "url": "https://toutiao.china.com/s_ayjr/xw/toutiao1/13000098/20240906/47171683.html?ayjr"
        },
        {
            "title": "山西传媒学院外一女子被杀害抛尸？官方通报",
            "url": "https://toutiao.china.com/s_ayjr/xw/toutiao1/13000098/20240906/47171684.html?ayjr"
        },
        {
            "title": "退钱哥希望大家记住落后就要挨打 但我们不要放弃",
            "url": "https://toutiao.china.com/s_ayjr/xw/toutiao1/13000098/20240906/47171685.html?ayjr"
        },
        {
            "title": "太缺钱了，英特尔被曝准备“贱卖”Mobileye股份",
            "url": "https://toutiao.china.com/s_ayjr/xw/toutiao1/13000098/20240906/47171686.html?ayjr"
        }
    ],
    "text": [
        [
            {
                "title": "北京将向公职人员配售保障房？北京住建委表示没有最新政策",
                "url": "https://toutiao.china.com/s_ayjr/xw/toutiao1/13000098/20240906/47168840.html?ayjr"
            }
        ],
        [
            {
                "title": "日澳外长防长会晤同意加强防务合作、支持菲律宾海警，外交部回应",
                "url": "https://toutiao.china.com/s_ayjr/xw/toutiao1/13000098/20240906/47168843.html?ayjr"
            }
        ],
        [
            {
                "title": "中国行我也行？通用汽车将在巴西推乙醇混动汽车",
                "url": "https://toutiao.china.com/s_ayjr/xw/toutiao1/13000098/20240906/47168844.html?ayjr"
            }
        ],
        [
            {
                "title": "5名严重刑事案件嫌犯潜逃，陕西咸阳警方发布悬赏！",
                "url": "https://toutiao.china.com/s_ayjr/xw/toutiao1/13000098/20240906/47168845.html?ayjr"
            }
        ],
        [
            {
                "title": "央行：降准还有一定空间，存贷款利率进一步下行面临一定约束",
                "url": "https://toutiao.china.com/s_ayjr/xw/toutiao1/13000098/20240906/47168846.html?ayjr"
            }
        ],
        [
            {
                "title": "中国已停止国际收养计划？外交部回应",
                "url": "https://toutiao.china.com/s_ayjr/xw/toutiao1/13000098/20240906/47168847.html?ayjr"
            }
        ],
        [
            {
                "title": "山东临沂一镇纪委书记酒驾关门挡脸拒下车接受检查？镇政府：已停职",
                "url": "https://toutiao.china.com/s_ayjr/xw/toutiao1/13000098/20240906/47168848.html?ayjr"
            }
        ],
        [
            {
                "title": "强奸可判死刑！印女医生遭奸杀事发邦修改法案",
                "url": "https://toutiao.china.com/s_ayjr/xw/toutiao1/13000098/20240906/47168841.html?ayjr"
            }
        ],
        [
            {
                "title": "洪中：“横向补贴”祖传秘方失效，大众怪得着中国吗？",
                "url": "https://toutiao.china.com/s_ayjr/xw/toutiao1/13000098/20240906/47168849.html?ayjr"
            }
        ],
        [
            {
                "title": "受西瓜皮启发，我国科研团队提出新型离子传输膜设计策略",
                "url": "https://toutiao.china.com/s_ayjr/xw/toutiao1/13000098/20240906/47168850.html?ayjr"
            }
        ],
        [
            {
                "title": "非洲朋友爱上中式豆浆，中国种植技术走进非洲村庄助发展",
                "url": "https://toutiao.china.com/s_ayjr/xw/toutiao1/13000098/20240906/47168851.html?ayjr"
            }
        ],
        [
            {
                "title": "三菱怂恿日本政府：得出手啊，中国对手太强大",
                "url": "https://toutiao.china.com/s_ayjr/xw/toutiao1/13000098/20240906/47168852.html?ayjr"
            }
        ],
        [
            {
                "title": "法国前总理菲利普宣布参选总统，“他认为马克龙撑不了几个月”",
                "url": "https://toutiao.china.com/s_ayjr/xw/toutiao1/13000098/20240906/47168853.html?ayjr"
            }
        ],
        [
            {
                "title": "设计时速350公里，杭温高铁9月6日开通运营",
                "url": "https://toutiao.china.com/s_ayjr/xw/toutiao1/13000098/20240906/47168854.html?ayjr"
            }
        ],
        [
            {
                "title": "前总理哈西娜政府垮台后，孟加拉国又掀起反印度浪潮",
                "url": "https://toutiao.china.com/s_ayjr/xw/toutiao1/13000098/20240906/47168842.html?ayjr"
            }
        ],
        [
            {
                "title": "百万粉丝网红称鱼塘遭村民哄抢，村干部：他为流量喊我们来",
                "url": "https://toutiao.china.com/s_ayjr/xw/toutiao1/13000098/20240906/47168855.html?ayjr"
            }
        ],
        [
            {
                "title": "央视回应无法转播“国足战日本”比赛：虽经反复争取，对方报价仍极度畸高",
                "url": "https://toutiao.china.com/s_ayjr/xw/toutiao1/13000098/20240906/47168816.html?ayjr"
            }
        ],
        [
            {
                "title": "国足首发阵容出炉，武磊张玉宁蒋光太上场，阿兰与费南多替补",
                "url": "https://toutiao.china.com/s_ayjr/xw/toutiao1/13000098/20240906/47168817.html?ayjr"
            }
        ],
        [
            {
                "title": "WTTC：中国或在十年内成为全球最大旅游市场",
                "url": "https://toutiao.china.com/s_ayjr/xw/toutiao1/13000098/20240906/47168818.html?ayjr"
            }
        ],
        [
            {
                "title": "南非国家行政学院院长：为什么中国式民主，对非洲人很重要？",
                "url": "https://toutiao.china.com/s_ayjr/xw/toutiao1/13000098/20240906/47168819.html?ayjr"
            }
        ],
        [
            {
                "title": "光刻机巨头CEO：美对华出口管制更加出于“经济动机”",
                "url": "https://toutiao.china.com/s_ayjr/xw/toutiao1/13000098/20240906/47168820.html?ayjr"
            }
        ]
    ]
}