{
    "hot": [
        {
            "headlines": [
                {
                    "title": "印度女子遭强奸体内现150ml精液后 又有4岁女童",
                    "url": "https://toutiao.china.com/s_ayjr/xw/toutiao1/13000098/20240823/47085822.html?ayjr"
                }
            ],
            "list": [
                [
                    {
                        "title": "市民投诉深圳山姆店烤鸡中吃出＂子弹＂状异物 门店回应",
                        "url": "https://toutiao.china.com/s_ayjr/xw/toutiao1/13000098/20240823/47085813.html?ayjr"
                    }
                ],
                [
                    {
                        "title": "警惕！7 岁女孩自喷防晒剂后接近“白肺”，医生提醒：情况严重可危及生命",
                        "url": "https://toutiao.china.com/s_ayjr/xw/toutiao1/13000098/20240822/47084089.html?ayjr"
                    }
                ]
            ]
        },
        {
            "headlines": [
                {
                    "title": "互联网保险业务再迎规范：严禁无资质“挂靠”",
                    "url": "https://toutiao.china.com/s_ayjr/xw/toutiao1/13000098/20240822/47084094.html?ayjr"
                }
            ],
            "list": [
                [
                    {
                        "title": "时政微观察丨奖牌背后，闪耀新时代中国精神",
                        "url": "https://toutiao.china.com/s_ayjr/xw/toutiao1/13000098/20240822/47084095.html?ayjr"
                    }
                ]
            ]
        },
        {
            "headlines": [
                {
                    "title": "王楚钦：奥运单打出局跟球拍无关，没能适应三",
                    "url": "https://toutiao.china.com/s_ayjr/xw/toutiao1/13000098/20240822/47084098.html?ayjr"
                }
            ],
            "list": [
                [
                    {
                        "title": "芬兰国防部长：芬兰正与北约国家就其境内驻军事宜进行谈判",
                        "url": "https://toutiao.china.com/s_ayjr/xw/toutiao1/13000098/20240822/47084080.html?ayjr"
                    }
                ]
            ]
        },
        {
            "headlines": [
                {
                    "title": "美国军方：“林肯”号航母抵达中东",
                    "url": "https://toutiao.china.com/s_ayjr/xw/toutiao1/13000098/20240822/47084082.html?ayjr"
                }
            ],
            "list": [
                [
                    {
                        "title": "导弹防御（Missile Defense）",
                        "url": "https://toutiao.china.com/s_ayjr/xw/toutiao1/13000098/20240822/47084083.html?ayjr"
                    },
                    {
                        "title": "“日本游戏机在中国陷入苦战”",
                        "url": "https://toutiao.china.com/s_ayjr/xw/toutiao1/13000098/20240822/47084084.html?ayjr"
                    }
                ]
            ]
        }
    ],
    "focus": [
        {
            "title": "抢起来了！“悟空”火了之后，这几个地方都说“我这儿才是孙悟空老家”",
            "url": "https://toutiao.china.com/s_ayjr/xw/toutiao1/13000098/20240823/47085877.html?ayjr",
            "img": "https://img1.utuku.imgcdc.com/360x0/toutiao/20240822/37574fb2-81f6-497d-9743-b4c3b06018b1.jpg"
        },
        {
            "title": "五角大楼禁令被推翻，美法官裁定：美军不能拒绝艾滋感染者入伍",
            "url": "https://toutiao.china.com/s_ayjr/xw/toutiao1/13000098/20240823/47085878.html?ayjr",
            "img": "https://img0.utuku.imgcdc.com/360x0/toutiao/20240822/7c56c212-c7da-4fd2-b5d2-68af8247dbe3.jpg"
        }
    ],
    "smallImg": [
        {
            "title": "印度报告显示：超150名印度议员针对女性实施犯罪，16人涉嫌强奸",
            "url": "https://toutiao.china.com/s_ayjr/xw/toutiao1/13000098/20240823/47085869.html?ayjr",
            "img": "https://img2.utuku.imgcdc.com/360x0/toutiao/20240822/f443e606-0676-4b5c-bf11-bca43088246e.jpg"
        },
        {
            "title": "数万抗议者反对修订地方选举法，印尼国会宣布休会",
            "url": "https://toutiao.china.com/s_ayjr/xw/toutiao1/13000098/20240823/47085870.html?ayjr",
            "img": "https://img1.utuku.imgcdc.com/360x0/toutiao/20240822/bc4d54bf-1c83-4872-9b04-f89ce247cd8f.jpg"
        },
        {
            "title": "美国军营水污染恐致癌：约100万人受影响，超54万人索赔",
            "url": "https://toutiao.china.com/s_ayjr/xw/toutiao1/13000098/20240823/47085871.html?ayjr",
            "img": "https://img2.utuku.imgcdc.com/360x0/toutiao/20240822/aa2ea8e4-5f43-416e-b4e6-bb74b3f2786b.jpg"
        },
        {
            "title": "大地财险保山中心支公司被罚 50 万，涉虚挂个人代理业务套取手续费等",
            "url": "https://toutiao.china.com/s_ayjr/xw/toutiao1/13000098/20240823/47085872.html?ayjr",
            "img": "https://img3.utuku.imgcdc.com/360x0/toutiao/20240822/f76fa156-88ee-4b6f-908d-0a4bfa3fec25.jpg"
        }
    ],
    "midImg": [
        {
            "title": "“悟空”带火山西旅游，当地高速受益股价大涨",
            "url": "https://toutiao.china.com/s_ayjr/xw/toutiao1/13000098/20240823/47085865.html?ayjr",
            "img": "https://img2.utuku.imgcdc.com/360x0/toutiao/20240822/fd0f95b4-90bb-4909-96bd-f539a10ede52.jpg"
        },
        {
            "title": "始祖鸟在中国卖的好，亚玛芬体育扭亏为盈",
            "url": "https://toutiao.china.com/s_ayjr/xw/toutiao1/13000098/20240823/47085866.html?ayjr",
            "img": "https://img2.utuku.imgcdc.com/360x0/toutiao/20240822/8902a3a0-6b08-4fec-8447-9263a740fd41.jpg"
        },
        {
            "title": "碧桂园服务换帅后首份中期成绩单：增收但不增利",
            "url": "https://toutiao.china.com/s_ayjr/xw/toutiao1/13000098/20240823/47085867.html?ayjr",
            "img": "https://img2.utuku.imgcdc.com/360x0/toutiao/20240822/202856b2-9b41-4dea-8895-9ede733c5024.jpg"
        },
        {
            "title": "重庆警方：网传“互联网产业园发生命案，2人死亡”系谣言",
            "url": "https://toutiao.china.com/s_ayjr/xw/toutiao1/13000098/20240823/47085868.html?ayjr",
            "img": "https://img1.utuku.imgcdc.com/360x0/toutiao/20240822/0c2e99ae-6635-4be3-bb87-045a9f989ec0.jpg"
        }
    ],
    "bigImg": [
        {
            "title": "中方出手后，爱尔兰乳制品组织：欧盟赔偿奶农损失？",
            "url": "https://toutiao.china.com/s_ayjr/xw/toutiao1/13000098/20240823/47085879.html?ayjr",
            "img": "https://img1.utuku.imgcdc.com/360x0/toutiao/20240822/16176a49-684e-4d63-af7d-bff433048b6d.jpg"
        },
        {
            "title": "中国驻加拿大使馆提醒",
            "url": "https://toutiao.china.com/s_ayjr/xw/toutiao1/13000098/20240823/47085860.html?ayjr",
            "img": "https://img2.utuku.imgcdc.com/650x0/toutiao/20240823/9c06f7f8-dcaf-440c-96a1-b78acfd65b5e.jpg"
        },
        {
            "title": "湖南一养猪场爆炸致7死，10人被判刑",
            "url": "https://toutiao.china.com/s_ayjr/xw/toutiao1/13000098/20240823/47085861.html?ayjr",
            "img": "https://img2.utuku.imgcdc.com/360x0/toutiao/20240823/8731ea9b-a5fb-4d57-9d71-b5f8cf2383bf.jpg"
        },
        {
            "title": "泰国一小型飞机坠毁，载5名中国乘客",
            "url": "https://toutiao.china.com/s_ayjr/xw/toutiao1/13000098/20240823/47085862.html?ayjr",
            "img": "https://img2.utuku.imgcdc.com/360x0/toutiao/20240823/bd54714b-d2b4-4f0a-a8d1-ec2840cb2632.jpg"
        }
    ],
    "imgText": [
        {
            "title": "“日本游戏机在中国陷入苦战”",
            "url": "https://toutiao.china.com/s_ayjr/xw/toutiao1/13000098/20240822/47084084.html?ayjr"
        },
        {
            "title": "西藏自治区政府原副主席王勇被逮捕",
            "url": "https://toutiao.china.com/s_ayjr/xw/toutiao1/13000098/20240822/47084085.html?ayjr"
        },
        {
            "title": "男子献血8次，用血时却被告知用不上？多方回应",
            "url": "https://toutiao.china.com/s_ayjr/xw/toutiao1/13000098/20240822/47084086.html?ayjr"
        },
        {
            "title": "樊振东、马龙、陈梦退出澳门冠军赛，王楚钦、孙颖莎将出战",
            "url": "https://toutiao.china.com/s_ayjr/xw/toutiao1/13000098/20240822/47084087.html?ayjr"
        },
        {
            "title": "热搜第一！王楚钦解释奥运单打出局原因",
            "url": "https://toutiao.china.com/s_ayjr/xw/toutiao1/13000098/20240822/47084088.html?ayjr"
        }
    ],
    "text": [
        [
            {
                "title": "因“赋红码”事件被处分的女官员改任郑州文旅局党组书记，官方回应",
                "url": "https://toutiao.china.com/s_ayjr/xw/toutiao1/13000098/20240822/47081526.html?ayjr"
            }
        ],
        [
            {
                "title": "佩洛西拒绝道歉",
                "url": "https://toutiao.china.com/s_ayjr/xw/toutiao1/13000098/20240822/47081507.html?ayjr"
            }
        ],
        [
            {
                "title": "美专家：美国允许服用兴奋剂运动员继续比赛 充当“间谍”选手",
                "url": "https://toutiao.china.com/s_ayjr/xw/toutiao1/13000098/20240822/47081508.html?ayjr"
            }
        ],
        [
            {
                "title": "招商局集团再查金融干部，招商银行原副行长丁伟落马，曾主抓招行零售二次转型",
                "url": "https://toutiao.china.com/s_ayjr/xw/toutiao1/13000098/20240822/47081509.html?ayjr"
            }
        ],
        [
            {
                "title": "四川成都发布高温红色预警信号",
                "url": "https://toutiao.china.com/s_ayjr/shsy/gundong/13000120/20240822/47080689.html?ayjr"
            }
        ],
        [
            {
                "title": "我军舰艇与埃及海军海上联训 现场画面来了！",
                "url": "https://toutiao.china.com/s_ayjr/shsy/gundong/13000120/20240822/47080641.html?ayjr"
            }
        ],
        [
            {
                "title": "海上扫雷！来看南海海域反水雷实兵对抗演练",
                "url": "https://toutiao.china.com/s_ayjr/shsy/gundong/13000120/20240822/47079844.html?ayjr"
            }
        ],
        [
            {
                "title": "观察者网对话曹锦清：如何认识邓小平和小平思想的当代传承",
                "url": "https://toutiao.china.com/s_ayjr/xw/toutiao1/13000098/20240822/47081505.html?ayjr"
            }
        ],
        [
            {
                "title": "“林肯”号航母已进入这一区域",
                "url": "https://toutiao.china.com/s_ayjr/shsy/gundong3/13000181/20240822/47079198.html?ayjr"
            }
        ],
        [
            {
                "title": "网管未删测试账号，境外论坛现我国某企业内部数据",
                "url": "https://toutiao.china.com/s_ayjr/shsy/gundong/13000120/20240822/47079179.html?ayjr"
            }
        ],
        [
            {
                "title": "今日处暑 你感受到秋意了吗？",
                "url": "https://toutiao.china.com/s_ayjr/shsy/gundong/13000120/20240822/47079027.html?ayjr"
            }
        ],
        [
            {
                "title": "联合国官员：和平无望 加沙人在等待死亡",
                "url": "https://toutiao.china.com/s_ayjr/shsy/gundong3/13000181/20240822/47079010.html?ayjr"
            }
        ],
        [
            {
                "title": "消息人士称加沙停火谈判陷入僵局",
                "url": "https://toutiao.china.com/s_ayjr/shsy/gundong3/13000181/20240822/47078999.html?ayjr"
            }
        ],
        [
            {
                "title": "英国调查记者：加沙人道主义危机暴露美国真面目",
                "url": "https://toutiao.china.com/s_ayjr/shsy/gundong3/13000181/20240822/47078867.html?ayjr"
            }
        ],
        [
            {
                "title": "吉利坚持自身转型路线，“已看到重返辉煌的曙光”",
                "url": "https://toutiao.china.com/s_ayjr/xw/toutiao1/13000098/20240822/47081506.html?ayjr"
            }
        ],
        [
            {
                "title": "石磐启：“孟加拉综合症”会在“一带一路”沿线蔓延吗？",
                "url": "https://toutiao.china.com/s_ayjr/xw/toutiao1/13000098/20240822/47078594.html?ayjr"
            }
        ],
        [
            {
                "title": "美国继续“拱火”，重提对菲5亿美元军援",
                "url": "https://toutiao.china.com/s_ayjr/xw/toutiao1/13000098/20240822/47078595.html?ayjr"
            }
        ],
        [
            {
                "title": "日本 46 人河川戏水后上吐下泻！或因河水引发传染病",
                "url": "https://toutiao.china.com/s_ayjr/xw/toutiao1/13000098/20240822/47078596.html?ayjr"
            }
        ],
        [
            {
                "title": "普京最担心的事情发生了，“铁哥们”要退群？",
                "url": "https://toutiao.china.com/s_ayjr/xw/toutiao1/13000098/20240822/47078597.html?ayjr"
            }
        ],
        [
            {
                "title": "广西柳州警方通报“烧烤店多人斗殴”：因感情纠纷引发打架，8 名嫌疑人已被抓捕归案",
                "url": "https://toutiao.china.com/s_ayjr/xw/toutiao1/13000098/20240822/47078598.html?ayjr"
            }
        ],
        [
            {
                "title": "东莞市原市长李毓全被查！今年 71 岁",
                "url": "https://toutiao.china.com/s_ayjr/xw/toutiao1/13000098/20240822/47078599.html?ayjr"
            }
        ]
    ]
}