{
    "focus": [
        {
            "title": "三亚海棠湾品质楼盘推荐 单价14800元/㎡起",
            "url": "http://sanya.focus.cn/daogou/11215548.html",
            "img": "http://imgs.focus.cn/upload/pics/38628/a_386271439.jpg"
        },
        {
            "title": "凭什么这么贵 普通人可买不起的别墅大搜罗",
            "url": "http://sanya.focus.cn/daogou/11211431.html",
            "img": "http://imgs.focus.cn/upload/pics/38622/a_386215391.jpg"
        },
        {
            "title": "陵水养生别墅大盘点 4居室美景房任你选",
            "url": "http://sanya.focus.cn/daogou/11211413.html",
            "img": "http://imgs.focus.cn/upload/pics/38622/b_386214468.jpg"
        }
    ],
    "midImg": [
        {
            "title": "雅居乐清水湾",
            "url": "http://sanya.focus.cn/loupan/2220006.html",
            "img": "http://i1.f.itc.cn/thumb/240/sanya/8114/b_81139924.jpg"
        },
        {
            "title": "雅居乐清水湾别墅",
            "url": "http://sanya.focus.cn/loupan/2220385.html",
            "img": "http://i1.f.itc.cn/thumb/240/sanya/29414/a_294138811.jpg"
        },
        {
            "title": "椰林居养生花园",
            "url": "http://sanya.focus.cn/loupan/2220123.html",
            "img": "http://i2.f.itc.cn/thumb/240/sanya/8135/a_81342281.jpg"
        },
        {
            "title": "圣河湾",
            "url": "http://sanya.focus.cn/loupan/2220018.html",
            "img": "http://imgs.focus.cn/thumb/240/sanya/38012/b_380113824.jpg"
        },
        {
            "title": "碧桂园珊瑚宫殿别墅",
            "url": "http://sanya.focus.cn/loupan/2220392.html",
            "img": "http://i1.f.itc.cn/thumb/240/sanya/37148/b_371478046.jpg"
        },
        {
            "title": "碧桂园珊瑚宫殿",
            "url": "http://sanya.focus.cn/loupan/2220067.html",
            "img": "http://imgs.focus.cn/thumb/240/sanya/37349/b_373486986.jpg"
        },
        {
            "title": "海云轩",
            "url": "http://sanya.focus.cn/loupan/2220298.html",
            "img": "http://i1.f.itc.cn/thumb/240/sanya/10972/b_109714300.jpg"
        },
        {
            "title": "弗拉明戈屿海",
            "url": "http://sanya.focus.cn/loupan/2220185.html",
            "img": "http://imgs.focus.cn/thumb/240/sanya/16235/a_162342231.jpg"
        }
    ],
    "text": [
        [
            {
                "url": "http://sanya.focus.cn/news/2016-10-27/11215469.html",
                "title": "三亚市委推行指尖办公 做到件件有着落事事有回音"
            }
        ],
        [
            {
                "url": "http://sanya.focus.cn/news/2016-10-27/11215468.html",
                "title": "明年想让海口市政府给您办啥事？快点进来提建议"
            }
        ],
        [
            {
                "url": "http://sanya.focus.cn/news/2016-10-27/11215463.html",
                "title": "三亚吉阳\"产业+就业\"绽放脱贫梦 贫困户将住新房"
            }
        ],
        [
            {
                "url": "http://sanya.focus.cn/news/2016-10-27/11215461.html",
                "title": "三亚半岭温泉投1亿多元建地下综合管廊 可用100年"
            }
        ],
        [
            {
                "url": "http://sanya.focus.cn/news/2016-10-27/11215456.html",
                "title": "9省市高考报名时间确定 随迁子女报名有啥门槛"
            }
        ],
        [
            {
                "title": "买房不被忽悠 盘点三亚那些五证齐全的房子",
                "url": "http://sanya.focus.cn/daogou/11211355.html"
            }
        ],
        [
            {
                "title": "海景公寓好户型该注意什么？ 小编来告诉您",
                "url": "http://sanya.focus.cn/daogou/11210961.html"
            }
        ],
        [
            {
                "title": "卧室自带精美飘窗 低密花园洋房8600元起",
                "url": "http://sanya.focus.cn/daogou/11210811.html"
            }
        ],
        [
            {
                "title": "常见六大购房纠纷 买房过程中注意事项必知",
                "url": "http://sanya.focus.cn/daogou/11208723.html"
            }
        ],
        [
            {
                "title": "只有低价可不够 买养老房还要注意哪些方面?",
                "url": "http://sanya.focus.cn/daogou/11209052.html"
            }
        ],
        [
            {
                "url": "http://home.focus.cn/news/2015-10-13/439170.html",
                "title": "打造个性化空间 3款时尚定制衣柜推荐"
            }
        ],
        [
            {
                "url": "http://home.focus.cn/news/2015-10-13/439168.html",
                "title": "听说，这样装大白墙能治愈性冷淡！"
            }
        ],
        [
            {
                "url": "http://home.focus.cn/news/2015-10-13/439166.html",
                "title": "浴室镜子有雾气？小编来支招"
            }
        ],
        [
            {
                "url": "http://home.focus.cn/news/2015-10-12/439139.html",
                "title": "80后孝顺女为父母翻新 改造83平美式小2居"
            }
        ],
        [
            {
                "url": "http://home.focus.cn/news/2015-10-12/439131.html",
                "title": "扮靓收纳两不误 3款简约实用梳妆台推荐"
            }
        ],
        [
            {
                "url": "http://home.focus.cn/news/2015-10-12/439130.html",
                "title": "舒适洁净更省心  3款节水型坐便器推荐"
            }
        ],
        [
            {
                "title": "多省份加入儿科联盟 海南孩子得病能转广州治",
                "url": "http://sanya.focus.cn/news/2016-10-27/11215454.html"
            }
        ],
        [
            {
                "title": "三亚凤凰机场：符合乘机规定的充电宝可携带上机",
                "url": "http://sanya.focus.cn/news/2016-10-27/11215425.html"
            }
        ],
        [
            {
                "title": "保亭新政花园交房超期2年仍是荒地 开发商:将退款",
                "url": "http://sanya.focus.cn/news/2016-10-27/11215416.html"
            }
        ],
        [
            {
                "title": "20余省份公布前三季度经济数据 多地GDP增速回升",
                "url": "http://sanya.focus.cn/news/2016-10-27/11215412.html"
            }
        ],
        [
            {
                "title": "房产税靴子要落了？不是房价利空，反是利好？",
                "url": "http://sanya.focus.cn/news/2016-10-27/11215407.html"
            }
        ],
        [
            {
                "title": "10月26日楼市：三亚签约71套 海口签约297套",
                "url": "http://sanya.focus.cn/news/2016-10-27/11215393.html"
            }
        ],
        [
            {
                "title": "国土部：建议调整库存压力较大城市土地供应计划",
                "url": "http://sanya.focus.cn/news/2016-10-27/11214801.html"
            }
        ],
        [
            {
                "title": "今起云南各州市职工可用住房公积金在昆明买房",
                "url": "http://sanya.focus.cn/news/2016-10-27/11214771.html"
            }
        ],
        [
            {
                "title": "报告称中国房地产行业兼并将增加",
                "url": "http://sanya.focus.cn/news/2016-10-27/11214748.html"
            }
        ],
        [
            {
                "title": "[雅居乐清水湾]项目现房在售 全款82折",
                "url": "http://sanya.focus.cn/loupan/2220006/lpdt851558.html"
            }
        ],
        [
            {
                "title": "[雅居乐山海间别墅]陵水别墅370万/栋起",
                "url": "http://sanya.focus.cn/loupan/2220380/lpdt851546.html"
            }
        ],
        [
            {
                "title": "[雅居乐山海间]购房全款、按揭现场有优惠",
                "url": "http://sanya.focus.cn/loupan/2220336/lpdt851553.html"
            }
        ],
        [
            {
                "title": "[雅居乐清水湾别墅]项目全款82折",
                "url": "http://sanya.focus.cn/loupan/2220385/lpdt851532.html"
            }
        ],
        [
            {
                "title": "椰林居养生花园带装修起价7500元/平",
                "url": "http://sanya.focus.cn/loupan/2220123/lpdt850965.html"
            }
        ]
    ]
}