{
    "focus": [
        {
            "title": "电影《祝你幸福！》发布情感主题曲《莫怕莫怕》",
            "url": "https://toutiao.china.com/s_ayyl/ylsy/gundong/13000142/20240827/47107420.html?ayyl",
            "img": "https://img3.utuku.imgcdc.com/650x0/ent/20240827/033d1d55-116a-4565-98f7-157deb52b6e4.jpg"
        },
        {
            "title": "杨洋黑粉登报公开致歉：已经完全认识到自己的错误",
            "url": "https://toutiao.china.com/s_ayyl/ylsy/gundong/13000142/20240827/47107167.html?ayyl",
            "img": "https://img0.utuku.imgcdc.com/650x0/ent/20240827/e8c2978f-c581-4b75-b18b-ea73c3ced25c.jpg"
        },
        {
            "title": "于正确认吴谨言王星越二搭《坠落春夜》：都好喜欢",
            "url": "https://toutiao.china.com/s_ayyl/ylsy/gundong/13000142/20240827/47107146.html?ayyl",
            "img": "https://img3.utuku.imgcdc.com/650x0/ent/20240827/9ab0e7eb-c394-4c4c-8a5b-1b1f82a5d110.jpg"
        }
    ],
    "midImg": [
        {
            "title": "TF三代成团承诺不私联 TFBOYS时代少年团送祝福",
            "url": "https://toutiao.china.com/s_ayyl/ylsy/gundong/13000142/20240827/47107046.html?ayyl",
            "img": "https://img3.utuku.imgcdc.com/650x0/ent/20240827/db5bb9f0-44ae-45f2-bfc4-274b59279ef5.jpg"
        },
        {
            "title": "《黑神话：悟空》爆火，哪版“齐天大圣”最惊艳？",
            "url": "https://toutiao.china.com/s_ayyl/ylsy/gundong/13000142/20240827/47107034.html?ayyl",
            "img": "https://img2.utuku.imgcdc.com/650x0/ent/20240827/6aad6793-3666-4c30-a613-efd2ce277e26.png"
        },
        {
            "title": "南派三叔回应吴邪选角：好演员塑造能力可征服观众",
            "url": "https://toutiao.china.com/s_ayyl/ylsy/gundong/13000142/20240827/47107005.html?ayyl",
            "img": "https://img2.utuku.imgcdc.com/650x0/ent/20240827/3a8b7ad0-1112-468f-9b5d-4b2e87027d5f.jpg"
        },
        {
            "title": "朱正廷程潇舞台上演性感双人舞 对视挑下巴CP感足",
            "url": "https://toutiao.china.com/s_ayyl/ylsy/gundong/13000142/20240827/47106742.html?ayyl",
            "img": "https://img1.utuku.imgcdc.com/650x0/ent/20240827/8ff65918-26d0-43f7-a891-daea4e9e6e08.jpg"
        },
        {
            "title": "东方甄选回应与董宇辉争议 否认组织恶意攻击对方",
            "url": "https://toutiao.china.com/s_ayyl/ylsy/gundong/13000142/20240827/47106960.html?ayyl",
            "img": "https://img2.utuku.imgcdc.com/650x0/ent/20240827/91223262-040b-4da1-a858-1ec874973503.jpg"
        },
        {
            "title": "陈奕迅19岁女儿恋情曝光？男方为日本混血男模",
            "url": "https://toutiao.china.com/s_ayyl/ylsy/gundong/13000142/20240827/47106948.html?ayyl",
            "img": "https://img3.utuku.imgcdc.com/650x0/ent/20240827/50c48d6f-7376-4bca-b3c9-97f2fbf48517.jpg"
        },
        {
            "title": "庞博文回应给粉丝“立规矩”：本意并不是想要训粉",
            "url": "https://toutiao.china.com/s_ayyl/ylsy/gundong/13000142/20240827/47107119.html?ayyl",
            "img": "https://img3.utuku.imgcdc.com/402x0/ent/20240827/71d9fcac-4bd8-47e5-8b83-c43897d7d0a7.png"
        },
        {
            "title": "乐评人梁源发文力挺派克特 宣布将起诉乙游粉丝",
            "url": "https://toutiao.china.com/s_ayyl/ylsy/gundong/13000142/20240827/47107110.html?ayyl",
            "img": "https://img2.utuku.imgcdc.com/560x0/ent/20240827/2dcf2f0f-36e5-4c7a-b067-145e6bbf8cbd.jpg"
        }
    ],
    "text": [
        [
            {
                "title": "数字音乐产业大会将发2023产业报告：中国2031年或成全球第二大音乐市场",
                "url": "https://toutiao.china.com/s_ayyl/yl/sdkb/13000116/20240827/47105813.html?ayyl"
            }
        ],
        [
            {
                "title": "TVB老戏骨街头吃鱼蛋，毫无包袱接地气，网友：越来越像李若彤",
                "url": "https://toutiao.china.com/s_ayyl/yl/sdkb/13000116/20240827/47105814.html?ayyl"
            }
        ],
        [
            {
                "title": "TVB视后回应突然缺席新剧原因，称还有机会回巢拍剧，与最佳CP合体出席活动",
                "url": "https://toutiao.china.com/s_ayyl/yl/sdkb/13000116/20240827/47105815.html?ayyl"
            }
        ],
        [
            {
                "title": "看人下菜、口无遮拦，上综艺坏口碑的“周冬雨”们，把我看无语了",
                "url": "https://toutiao.china.com/s_ayyl/yl/sdkb/13000116/20240827/47105816.html?ayyl"
            }
        ],
        [
            {
                "title": "石川佳纯洗白评论区获中球迷安慰，疑暗恋马龙30岁不嫁，却参拜神社被男方取关",
                "url": "https://toutiao.china.com/s_ayyl/yl/sdkb/13000116/20240827/47105817.html?ayyl"
            }
        ],
        [
            {
                "title": "网友爆料大衣哥女儿朱雪梅开饭店当老板娘，站前台工作十分认真",
                "url": "https://toutiao.china.com/s_ayyl/yl/sdkb/13000116/20240827/47105818.html?ayyl"
            }
        ],
        [
            {
                "title": "张昊唯宣布离社交媒体，专心案件和维权官司",
                "url": "https://toutiao.china.com/s_ayyl/yl/sdkb/13000116/20240827/47105819.html?ayyl"
            }
        ],
        [
            {
                "title": "何超琼庆62岁大寿！单身多年仍风华绝代，过着无牵无挂的潇洒生活",
                "url": "https://toutiao.china.com/s_ayyl/yl/sdkb/13000116/20240827/47105820.html?ayyl"
            }
        ],
        [
            {
                "title": "三大厂牌混战，优酷白夜剧场登顶",
                "url": "https://toutiao.china.com/s_ayyl/yl/sdkb/13000116/20240827/47105792.html?ayyl"
            }
        ],
        [
            {
                "title": "董璇女儿太美了！8岁小酒窝和妈妈游韩国，新造型漂亮大方星范足",
                "url": "https://toutiao.china.com/s_ayyl/yl/sdkb/13000116/20240827/47105793.html?ayyl"
            }
        ],
        [
            {
                "title": "沈腾新片哑火，暑期档落下帷幕，时隔6年，沈腾终于正面赢了徐峥",
                "url": "https://toutiao.china.com/s_ayyl/yl/sdkb/13000116/20240827/47105794.html?ayyl"
            }
        ],
        [
            {
                "title": "62岁老戏骨郭凯敏，二婚娶尤勇前妻很幸福，儿子长相英俊比他帅",
                "url": "https://toutiao.china.com/s_ayyl/yl/sdkb/13000116/20240827/47105795.html?ayyl"
            }
        ],
        [
            {
                "title": "刘亦菲被利用？赵丽颖赢麻了？张若昀瓶颈期？敖瑞鹏恋情曝光？刘宇宁田曦薇的料？",
                "url": "https://toutiao.china.com/s_ayyl/yl/sdkb/13000116/20240827/47105796.html?ayyl"
            }
        ],
        [
            {
                "title": "黄子韬是在真人秀上表演求婚么？",
                "url": "https://toutiao.china.com/s_ayyl/yl/sdkb/13000116/20240827/47105797.html?ayyl"
            }
        ],
        [
            {
                "title": "央视力捧马凡舒转型，体育综艺都是“当家花旦”，手握8档新节目",
                "url": "https://toutiao.china.com/s_ayyl/yl/sdkb/13000116/20240827/47105798.html?ayyl"
            }
        ],
        [
            {
                "title": "孙雅诺：三首疗愈心灵的原创歌曲",
                "url": "https://toutiao.china.com/s_ayyl/yl/sdkb/13000116/20240827/47105799.html?ayyl"
            }
        ],
        [
            {
                "title": "瑞典76岁名帅埃里克森患癌去世 生涯曾获18座冠军奖杯",
                "url": "https://toutiao.china.com/s_ayyl/yl/sdkb/13000116/20240827/47105800.html?ayyl"
            }
        ],
        [
            {
                "title": "56岁男星自曝欠债千万，无儿无女母亲患癌，借了高利贷无力偿还",
                "url": "https://toutiao.china.com/s_ayyl/yl/sdkb/13000116/20240827/47105801.html?ayyl"
            }
        ],
        [
            {
                "title": "佟丽娅和黄明昊相差19岁，在新片演绎无臂女和听障男的感人故事",
                "url": "https://toutiao.china.com/s_ayyl/yl/sdkb/13000116/20240827/47105802.html?ayyl"
            }
        ],
        [
            {
                "title": "又一部惊艳新剧，一集更比一集精彩，第6集飙上9.1分！",
                "url": "https://toutiao.china.com/s_ayyl/yl/sdkb/13000116/20240827/47105785.html?ayyl"
            }
        ],
        [
            {
                "title": "2024年的暑假档电影，比2023年真心差太远了",
                "url": "https://toutiao.china.com/s_ayyl/yl/sdkb/13000116/20240827/47105786.html?ayyl"
            }
        ],
        [
            {
                "title": "【2024.8.25】可以讲一讲邱天吗？多部耽美小说都要影视化？女艺人为什么大部分都那么白？",
                "url": "https://toutiao.china.com/s_ayyl/yl/sdkb/13000116/20240827/47105787.html?ayyl"
            }
        ],
        [
            {
                "title": "鹿晗求婚关晓彤了？陈伟霆何穗分手？霍思燕夫妇被封杀？杨幂翻身了？王鹤棣被新丽压宝？",
                "url": "https://toutiao.china.com/s_ayyl/yl/sdkb/13000116/20240827/47105788.html?ayyl"
            }
        ],
        [
            {
                "title": "半退休！58岁林利抗癌成功后体能下降，曾与嫰妻房事不协调闹婚变",
                "url": "https://toutiao.china.com/s_ayyl/yl/sdkb/13000116/20240827/47105789.html?ayyl"
            }
        ],
        [
            {
                "title": "一问一答 | 黄子韬徐艺洋，迪丽热巴陈飞宇，赵露思，小眼睛男星，张颖颖，敖瑞鹏",
                "url": "https://toutiao.china.com/s_ayyl/yl/sdkb/13000116/20240827/47105790.html?ayyl"
            }
        ],
        [
            {
                "title": "一周上新|动画真人爱情片、陈丽君越剧电影收官暑期档，北美现象级恐怖热片上线",
                "url": "https://toutiao.china.com/s_ayyl/yl/sdkb/13000116/20240827/47105791.html?ayyl"
            }
        ],
        [
            {
                "title": "游吟诗人的一天",
                "url": "https://toutiao.china.com/s_ayyl/yl/sdkb/13000116/20240827/47105776.html?ayyl"
            }
        ],
        [
            {
                "title": "萧亚轩生日前浴室跌倒受伤！性感天后“复出”遥遥无期？",
                "url": "https://toutiao.china.com/s_ayyl/yl/sdkb/13000116/20240827/47105777.html?ayyl"
            }
        ],
        [
            {
                "title": "张兰直播官宣5个月后要当奶奶，汪小菲马筱梅坐在一旁，未否认怀孕喜讯",
                "url": "https://toutiao.china.com/s_ayyl/yl/sdkb/13000116/20240827/47105778.html?ayyl"
            }
        ],
        [
            {
                "title": "周深张碧晨获东方风云榜最佳男女歌手 时代少年团拿三奖现场比心",
                "url": "https://toutiao.china.com/s_ayyl/yl/sdkb/13000116/20240827/47105779.html?ayyl"
            }
        ]
    ]
}