{
    "focus": [
        {
            "title": "粤桂股份：公司未生产三氯蔗糖",
            "url": "https://toutiao.china.com/s_ayjr/aou/cj/13004011/20240906/47173784.html?ayjr",
            "img": "https://img2.utuku.imgcdc.com/360x0/toutiao/20240906/ea985b7b-3422-41a4-b8ad-d80ca3247abe.jpg"
        },
        {
            "title": "维信诺：公司在折叠领域储备较多领先技术，目前已供货多个品牌客户多款折叠产品",
            "url": "https://toutiao.china.com/s_ayjr/aou/cj/13004011/20240906/47173785.html?ayjr",
            "img": "https://img1.utuku.imgcdc.com/360x0/toutiao/20240906/39fa2e7c-68ea-475f-9aca-099de4da8741.jpg"
        },
        {
            "title": "深圳华强今日涨停 陈小群席位净卖出1.10亿元",
            "url": "https://toutiao.china.com/s_ayjr/aou/cj/13004011/20240906/47173786.html?ayjr",
            "img": "https://img1.utuku.imgcdc.com/360x0/toutiao/20240906/73028e63-83f3-40bb-a419-9a907e5ded1d.jpg"
        }
    ],
    "midImg": [
        {
            "title": "5连板伟时电子：公司自身不生产VR终端产品及空中成像的相关产品",
            "url": "https://toutiao.china.com/s_ayjr/aou/cj/13004011/20240906/47173769.html?ayjr",
            "img": "https://img2.utuku.imgcdc.com/360x0/toutiao/20240906/04c4bc0d-db19-4db9-ab70-19c5b4eee5f2.jpg"
        },
        {
            "title": "上海机场：现代运输方式主要包括航空运输、水路运输（含海运）、铁路运输、公路运输等",
            "url": "https://toutiao.china.com/s_ayjr/aou/cj/13004011/20240906/47173770.html?ayjr",
            "img": "https://img0.utuku.imgcdc.com/360x0/toutiao/20240906/a1a212c3-5400-4717-b18e-af06de0a9f76.jpg"
        },
        {
            "title": "海南椰岛：公司未持有离岛免税许可 跨境电商业务已停业",
            "url": "https://toutiao.china.com/s_ayjr/aou/cj/13004011/20240906/47173771.html?ayjr",
            "img": "https://img2.utuku.imgcdc.com/360x0/toutiao/20240906/288c607e-7f33-4684-b879-f5aa3a9017fe.jpg"
        },
        {
            "title": "马斯克1.5亿美元在北京买房？特斯拉方面回应：假消息，纯炒作",
            "url": "https://toutiao.china.com/s_ayjr/aou/cj/13004011/20240906/47173772.html?ayjr",
            "img": "https://img2.utuku.imgcdc.com/360x0/toutiao/20240906/d88eb9ae-f6bc-4dfa-9ad5-5623b3cdc7f0.jpg"
        },
        {
            "title": "丰乐种业：目前公司未接到控股股东国投种业拟向公司注入资产的相关信息",
            "url": "https://toutiao.china.com/s_ayjr/aou/cj/13004011/20240906/47173773.html?ayjr",
            "img": "https://img0.utuku.imgcdc.com/360x0/toutiao/20240906/51a46b4d-933e-467c-aee1-59a9b958dc04.jpg"
        },
        {
            "title": "未被央视直播的国足惨败：转播费用“畸高” 赛事版权市场已大降温",
            "url": "https://toutiao.china.com/s_ayjr/aou/cj/13004011/20240906/47173774.html?ayjr",
            "img": "https://img0.utuku.imgcdc.com/360x0/toutiao/20240906/d5011d9b-f20d-448f-a3e8-b5ab220b7102.jpg"
        },
        {
            "title": "亚通精工：公司正加强应收款项的催收",
            "url": "https://toutiao.china.com/s_ayjr/aou/cj/13004011/20240906/47173765.html?ayjr",
            "img": "https://img2.utuku.imgcdc.com/360x0/toutiao/20240906/2b4d05ca-892a-488c-ba40-55f6a6b3f3a9.jpg"
        },
        {
            "title": "贵广网络：公司有在网络传输等多个领域与华为开展友好合作",
            "url": "https://toutiao.china.com/s_ayjr/aou/cj/13004011/20240906/47173766.html?ayjr",
            "img": "https://img3.utuku.imgcdc.com/360x0/toutiao/20240906/69fbb112-3c03-47f3-b159-5a4aa294c0c5.jpg"
        }
    ],
    "text": [
        [
            {
                "title": "国元证券给予吉贝尔买入评级：盈利能力改善，在研创新药临床有序推进",
                "url": "https://toutiao.china.com/s_ayjr/aou/cj/13004011/20240906/47173728.html?ayjr"
            }
        ],
        [
            {
                "title": "海南椰岛：椰岛草本酱香酒生产及营销分别由椰岛贵州酒业公司与椰岛生态酒公司负责运营",
                "url": "https://toutiao.china.com/s_ayjr/aou/cj/13004011/20240906/47173729.html?ayjr"
            }
        ],
        [
            {
                "title": "上工申贝：公司的美国子公司SGIA已经获得美国FAA的TC认证",
                "url": "https://toutiao.china.com/s_ayjr/aou/cj/13004011/20240906/47173730.html?ayjr"
            }
        ],
        [
            {
                "title": "推动“闽菜进京”，全聚德携手福州老字号聚春园打造非遗联名宴",
                "url": "https://toutiao.china.com/s_ayjr/aou/cj/13004011/20240906/47173731.html?ayjr"
            }
        ],
        [
            {
                "title": "信安世纪： 公司产品和解决方案不涉及量子通讯",
                "url": "https://toutiao.china.com/s_ayjr/aou/cj/13004011/20240906/47173732.html?ayjr"
            }
        ],
        [
            {
                "title": "安泰科技：超薄CVD金刚石膜产品目前尚属于项目研发阶段",
                "url": "https://toutiao.china.com/s_ayjr/aou/cj/13004011/20240906/47173733.html?ayjr"
            }
        ],
        [
            {
                "title": "升级为F1全球合作伙伴 联想集团加速布局全球化",
                "url": "https://toutiao.china.com/s_ayjr/aou/cj/13004011/20240906/47173734.html?ayjr"
            }
        ],
        [
            {
                "title": "淮北矿业：公司下属的临涣焦化公司采用4×55孔6米JN60型焦炉生产焦炭",
                "url": "https://toutiao.china.com/s_ayjr/aou/cj/13004011/20240906/47173735.html?ayjr"
            }
        ],
        [
            {
                "title": "亿帆医药：公司主要从事医药产品、原料药和高分子材料的生产、研发与销售",
                "url": "https://toutiao.china.com/s_ayjr/aou/cj/13004011/20240906/47173736.html?ayjr"
            }
        ],
        [
            {
                "title": "江南布衣2024财年收入增长17.3%",
                "url": "https://toutiao.china.com/s_ayjr/aou/cj/13004011/20240906/47173737.html?ayjr"
            }
        ],
        [
            {
                "title": "暂时不必担心iPhone 16不能用微信了",
                "url": "https://toutiao.china.com/s_ayjr/aou/cj/13004011/20240906/47173738.html?ayjr"
            }
        ],
        [
            {
                "title": "昱能科技：股东嘉兴汇英拟减持不超150万股公司股份",
                "url": "https://toutiao.china.com/s_ayjr/aou/cj/13004011/20240906/47173739.html?ayjr"
            }
        ],
        [
            {
                "title": "天宇股份在浙江新设科技子公司",
                "url": "https://toutiao.china.com/s_ayjr/aou/cj/13004011/20240906/47173740.html?ayjr"
            }
        ],
        [
            {
                "title": "拟1.5亿元控股嘉洋电池延伸产业链 誉辰智能账上现金吃得消吗？",
                "url": "https://toutiao.china.com/s_ayjr/aou/cj/13004011/20240906/47173741.html?ayjr"
            }
        ],
        [
            {
                "title": "昱能科技： 股东计划减持公司股份",
                "url": "https://toutiao.china.com/s_ayjr/aou/cj/13004011/20240906/47173742.html?ayjr"
            }
        ],
        [
            {
                "title": "41家A股上市银行上半年净息差下探",
                "url": "https://toutiao.china.com/s_ayjr/aou/cj/13004011/20240906/47173743.html?ayjr"
            }
        ],
        [
            {
                "title": "324家公司获海外机构调研",
                "url": "https://toutiao.china.com/s_ayjr/aou/cj/13004011/20240906/47173744.html?ayjr"
            }
        ],
        [
            {
                "title": "璞泰来：公司在新能源电池材料和自动化设备业务上与远航锦锂均有合作",
                "url": "https://toutiao.china.com/s_ayjr/aou/cj/13004011/20240906/47173745.html?ayjr"
            }
        ],
        [
            {
                "title": "杭州银行副行长章建夫：净息差边际企稳 资产负债两端加力稳息差",
                "url": "https://toutiao.china.com/s_ayjr/aou/cj/13004011/20240906/47173708.html?ayjr"
            }
        ],
        [
            {
                "title": "锋尚文化：公司暂未参与玛利亚凯莉和侃爷（Kanye West）演唱会的承办",
                "url": "https://toutiao.china.com/s_ayjr/aou/cj/13004011/20240906/47173709.html?ayjr"
            }
        ],
        [
            {
                "title": "*ST中润：截至目前，杭州汇成所持公司股份未发生变化",
                "url": "https://toutiao.china.com/s_ayjr/aou/cj/13004011/20240906/47173710.html?ayjr"
            }
        ],
        [
            {
                "title": "2024年8月全国受理网络违法和不良信息举报1983.3万件",
                "url": "https://toutiao.china.com/s_ayjr/aou/cj/13004011/20240906/47173711.html?ayjr"
            }
        ],
        [
            {
                "title": "亿帆医药：目前亿立舒在欧洲为授权销售模式",
                "url": "https://toutiao.china.com/s_ayjr/aou/cj/13004011/20240906/47173712.html?ayjr"
            }
        ],
        [
            {
                "title": "美团“袋鼠宝贝之家”新增13家 落地广东、安徽等",
                "url": "https://toutiao.china.com/s_ayjr/aou/cj/13004011/20240906/47173713.html?ayjr"
            }
        ],
        [
            {
                "title": "淮北矿业：公司正在加快化工延链项目建设进度，年产10万吨碳酸二甲酯项目力争10月底前建成试生产",
                "url": "https://toutiao.china.com/s_ayjr/aou/cj/13004011/20240906/47173714.html?ayjr"
            }
        ],
        [
            {
                "title": "映翰通：目前公司与泽宇智能暂无业务往来",
                "url": "https://toutiao.china.com/s_ayjr/aou/cj/13004011/20240906/47173715.html?ayjr"
            }
        ],
        [
            {
                "title": "富春股份：公司自研产品《仙境传说RO：新世代的诞生》已在港澳台等地区成功运营多年",
                "url": "https://toutiao.china.com/s_ayjr/aou/cj/13004011/20240906/47173716.html?ayjr"
            }
        ],
        [
            {
                "title": "贵州三力：控股股东及一致行动人提前终止减持计划，已减持2.96%公司股份",
                "url": "https://toutiao.china.com/s_ayjr/aou/cj/13004011/20240906/47173717.html?ayjr"
            }
        ],
        [
            {
                "title": "iPhone 16定价或与上代整体持平 全系配备3nm处理器",
                "url": "https://toutiao.china.com/s_ayjr/aou/cj/13004011/20240906/47173718.html?ayjr"
            }
        ],
        [
            {
                "title": "建发股份换帅完成工商变更 林茂任建发股份董事长",
                "url": "https://toutiao.china.com/s_ayjr/aou/cj/13004011/20240906/47173719.html?ayjr"
            }
        ]
    ]
}