{
    "focus": [
        {
            "title": "大结局要来？美债全线收跌，耶伦在等中国专机，再借不到钱就破产",
            "url": "http://military.miercn.com/aoyou?aid=4596185",
            "img": "https://pic2.miercn.com/crawl/2409_yzThumb/11/f5d42f36c7813b63876.jpg"
        },
        {
            "title": "多国军舰到位，北约秘书长给中国两条路，中国一声不吭，准备硬刚",
            "url": "http://military.miercn.com/aoyou?aid=4596187",
            "img": "https://pic2.miercn.com/crawl/2409_yzThumb/11/cff3d3c2954c6dfc711.jpg"
        },
        {
            "title": "暴行发生时，美国甚至“起立鼓掌”！安瓦尔赞赏中俄立场",
            "url": "http://military.miercn.com/aoyou?aid=4596189",
            "img": "https://pic2.miercn.com/crawl/2409_yzThumb/11/8d7ccb64734c5212964.jpg"
        }
    ],
    "midImg": [
        {
            "title": "中国警告无效！德国军舰横穿台湾海峡，只有奉命撞击才能有效果？",
            "url": "http://military.miercn.com/aoyou?aid=4596181",
            "img": "https://pic2.miercn.com/crawl/2409_yzThumb/11/28df63f743d95be9724.jpg"
        },
        {
            "title": "中国真心被辜负？柬埔寨民调：从精英到平民，为何普遍亲美？",
            "url": "http://military.miercn.com/aoyou?aid=4596179",
            "img": "https://pic2.miercn.com/crawl/2409_yz/11/b5a81997ddec1978778.jpg"
        },
        {
            "title": "北约军“换皮”杀到前线！危难时刻，俄罗斯对中国的称呼变了",
            "url": "http://military.miercn.com/aoyou?aid=4596177",
            "img": "https://pic2.miercn.com/crawl/2409_yzThumb/11/0a19cc85551d5c65475.jpg"
        },
        {
            "title": "战斗在深夜打响！144架无人机突袭，俄9个州被炸，乌美英法德失声",
            "url": "http://military.miercn.com/aoyou?aid=4596183",
            "img": "https://pic2.miercn.com/crawl/2409_yzThumb/11/8086a0489724b640292.jpg"
        },
        {
            "title": "越南和菲律宾签协议，暗戳戳地表达不满，却我们一招断了后路",
            "url": "http://military.miercn.com/aoyou?aid=4596120",
            "img": "https://pic2.miercn.com/contribute/month_2409/20240910153744888.jpg"
        },
        {
            "title": "突发！伊朗和以色列海上开打，伊朗太生猛了，美国两艘航母镇不住",
            "url": "http://military.miercn.com/aoyou?aid=4596116",
            "img": "https://pic2.miercn.com/crawl/2409_yzThumb/10/a5f231587bed3072995.jpg"
        },
        {
            "title": "重大突破！全球稀缺资源，中国新增1亿吨，掐美国脖子的来了...",
            "url": "http://military.miercn.com/aoyou?aid=4596118",
            "img": "https://pic2.miercn.com/contribute/month_2409/20240910154732420.jpg"
        },
        {
            "title": "中国和拉美干了一件大事",
            "url": "http://military.miercn.com/aoyou?aid=4596114",
            "img": "https://pic2.miercn.com/contribute/month_2409/20240911090854151.jpg"
        }
    ],
    "text": [
        [
            {
                "title": "战斗在深夜打响，以色列不宣而战，进攻第三国，已造成数十人伤亡",
                "url": "http://military.miercn.com/aoyou?aid=4596231"
            }
        ],
        [
            {
                "title": "柯文哲事件迎来新进展！黄国昌力挽狂澜！邱毅今献计能否翻转？",
                "url": "http://military.miercn.com/aoyou?aid=4596291"
            }
        ],
        [
            {
                "title": "埃尔多安为救哈马斯，做出了预言，以色列将会占领中东三个国家",
                "url": "http://military.miercn.com/aoyou?aid=4596247"
            }
        ],
        [
            {
                "title": "拒绝放弃仙宾礁，解放军在等电话，局面变33围1，名单上都是硬茬",
                "url": "http://military.miercn.com/aoyou?aid=4596217"
            }
        ],
        [
            {
                "title": "中方一锤定音，援助非洲3600亿元，联合国无法理解，要求停止借贷",
                "url": "http://military.miercn.com/aoyou?aid=4596287"
            }
        ],
        [
            {
                "title": "张口就来！联合国秘书长来华，张口就给中国扣上了一顶大帽子！",
                "url": "http://military.miercn.com/aoyou?aid=4596257"
            }
        ],
        [
            {
                "title": "全票通过，美国将禁止销售大疆无人机！外媒：技术水平跟不上人家",
                "url": "http://military.miercn.com/aoyou?aid=4596219"
            }
        ],
        [
            {
                "title": "哈里斯“舌战”特朗普，谁会是嘴强王者？",
                "url": "http://military.miercn.com/aoyou?aid=4596223"
            }
        ],
        [
            {
                "title": "中国海警动真格，菲海警被赶出九段线，关键时刻，中美司令通话",
                "url": "http://military.miercn.com/aoyou?aid=4596225"
            }
        ],
        [
            {
                "title": "中美通话，美国终于醒悟了？",
                "url": "http://military.miercn.com/aoyou?aid=4596293"
            }
        ],
        [
            {
                "title": "莫斯科警报一夜拉响，俄方发现乌克兰通过香港：秘密获得先进技术",
                "url": "http://military.miercn.com/aoyou?aid=4596207"
            }
        ],
        [
            {
                "title": "美媒承认：中国已彻底解决发动机问题！J-20A性能已经超越F-22",
                "url": "http://military.miercn.com/aoyou?aid=4596241"
            }
        ],
        [
            {
                "title": "中国拖船命令还没下，菲律宾先在仙宾礁划红线，要用武力顽抗到底",
                "url": "http://military.miercn.com/aoyou?aid=4596235"
            }
        ],
        [
            {
                "title": "榴莲堆积如山后，马科斯坐不住了，公开发文要与我国合作",
                "url": "http://military.miercn.com/aoyou?aid=4596277"
            }
        ],
        [
            {
                "title": "莫斯科已在乌军射程之内！普京扛不住了，突然改口：准备好谈判了",
                "url": "http://military.miercn.com/aoyou?aid=4596233"
            }
        ],
        [
            {
                "title": "中国试点外商独资医院，引起美国高度关注，认为机遇与挑战并存",
                "url": "http://military.miercn.com/aoyou?aid=4596279"
            }
        ],
        [
            {
                "title": "中方禁令正式生效后，美众议院通过法案，禁止中企对美出售无人机",
                "url": "http://military.miercn.com/aoyou?aid=4596239"
            }
        ],
        [
            {
                "title": "德国战机携核弹飞行，日本称撤走中国钓鱼岛浮标，重大变局来临！",
                "url": "http://military.miercn.com/aoyou?aid=4596267"
            }
        ],
        [
            {
                "title": "曼尼普尔邦，打响印度解体第一枪？这就是美国想看见的",
                "url": "http://military.miercn.com/aoyou?aid=4596271"
            }
        ],
        [
            {
                "title": "南海大结局倒计时，人民日报敲响钟声，对菲律宾下达最后通牒",
                "url": "http://military.miercn.com/aoyou?aid=4596203"
            }
        ],
        [
            {
                "title": "“中国工程师变废为宝，西方企业眼红”",
                "url": "http://military.miercn.com/aoyou?aid=4596273"
            }
        ],
        [
            {
                "title": "反华势力早晚合流！以色列最大英文报纸，呼吁“联合国纳入台湾”",
                "url": "http://military.miercn.com/aoyou?aid=4596229"
            }
        ],
        [
            {
                "title": "绍伊古：将乌军赶出俄领土前，俄方不会进行任何谈判",
                "url": "http://military.miercn.com/aoyou?aid=4596209"
            }
        ],
        [
            {
                "title": "俄罗斯亡，中国寒？非也！比西方围堵更可怕的，是我们的妄自菲薄",
                "url": "http://military.miercn.com/aoyou?aid=4596263"
            }
        ],
        [
            {
                "title": "非洲，对中国很重要！",
                "url": "http://military.miercn.com/aoyou?aid=4596251"
            }
        ],
        [
            {
                "title": "不宣而战，英国狗走上乌克兰战场，吓到了俄罗斯士兵",
                "url": "http://military.miercn.com/aoyou?aid=4596199"
            }
        ],
        [
            {
                "title": "中科大副院长：美国都造不出的光刻机，中国永远不可能造出来!",
                "url": "http://military.miercn.com/aoyou?aid=4596221"
            }
        ],
        [
            {
                "title": "大批乌军逃亡，泽连斯基这回押对了？北约改变战术，逼中国2选1",
                "url": "http://military.miercn.com/aoyou?aid=4596227"
            }
        ],
        [
            {
                "title": "今天，重要信号，大反攻已打响",
                "url": "http://military.miercn.com/aoyou?aid=4596283"
            }
        ],
        [
            {
                "title": "特朗普歃血为誓，不当选就让两国陨落？美国大选被普京玩弄于股掌",
                "url": "http://military.miercn.com/aoyou?aid=4596261"
            }
        ]
    ]
}