[
    {
        "key": "北大副教授林小英在《十三邀》里反对教育内卷，称「现在的教育系统似乎只为升学做预备」，如何评价？",
        "url": "https://www.zhihu.com/question/670845121?utm_source=aoyou",
        "count": 8790475,
        "tendency": 0
    },
    {
        "key": "向佐主演的《门前宝地》他的各种迷之动作那么尬，没人提醒他么？",
        "url": "https://www.zhihu.com/question/809274358?utm_source=aoyou",
        "count": 5491391,
        "tendency": 0
    },
    {
        "key": "重启价格战，宝马 3 系全系跌幅达 9.2 万，家用目前值得入手吗？",
        "url": "https://www.zhihu.com/question/864609699?utm_source=aoyou",
        "count": 5131786,
        "tendency": 0
    },
    {
        "key": "王楚钦、孙颖莎、王曼昱全部退出全锦赛，为何国乒几大主力纷纷退赛？赛程安排是否不合理？",
        "url": "https://www.zhihu.com/question/955229186?utm_source=aoyou",
        "count": 4516242,
        "tendency": 0
    },
    {
        "key": "如何找到愿意为之付出一生的研究事业？",
        "url": "https://www.zhihu.com/question/870573710?utm_source=aoyou",
        "count": 3556755,
        "tendency": 0
    },
    {
        "key": "刘强东章泽天夫妇称遭有组织造谣抹黑，警方正在侦办，具体情况如何？造谣者将承担哪些法律责任？",
        "url": "https://www.zhihu.com/question/1021575791?utm_source=aoyou",
        "count": 2754454,
        "tendency": 0
    },
    {
        "key": "三色雨布维权事件对迈巴赫品牌的调性影响有多大？",
        "url": "https://www.zhihu.com/question/991045537?utm_source=aoyou",
        "count": 2748904,
        "tendency": 0
    },
    {
        "key": "世预赛阿根廷 6:0 玻利维亚，梅西帽子戏法 + 两助，如何评价本场比赛？",
        "url": "https://www.zhihu.com/question/1027847977?utm_source=aoyou",
        "count": 1666242,
        "tendency": 0
    },
    {
        "key": "如何看待杨妞花把拐卖她的人贩子的名字从 5 岁记忆到 30 多岁？",
        "url": "https://www.zhihu.com/question/817400910?utm_source=aoyou",
        "count": 1317870,
        "tendency": 0
    },
    {
        "key": "天津取消住房限制性措施，进一步优化房地产政策，将对当地带来哪些影响？",
        "url": "https://www.zhihu.com/question/1021207007?utm_source=aoyou",
        "count": 1266913,
        "tendency": 0
    },
    {
        "key": "《红楼梦》中的宝钗做过哪些你无法理解的事情？",
        "url": "https://www.zhihu.com/question/554929326?utm_source=aoyou",
        "count": 1158968,
        "tendency": 0
    },
    {
        "key": "2025 年国考招录人数再创新高，近七成专招应届生，今年公务员报考有哪些新特点值得关注？",
        "url": "https://www.zhihu.com/question/922651423?utm_source=aoyou",
        "count": 1009945,
        "tendency": 0
    },
    {
        "key": "为什么薛姨妈和王夫人是亲姐妹，一个嫁到国公府成为诰命夫人，一个只能成为商人妇呢？",
        "url": "https://www.zhihu.com/question/38166310?utm_source=aoyou",
        "count": 1008997,
        "tendency": 0
    },
    {
        "key": "重庆一班主任在班级群内怒骂「都给老子滚」，被暂停职务，如何看待此事？教师情绪崩溃时该如何排解？",
        "url": "https://www.zhihu.com/question/943447099?utm_source=aoyou",
        "count": 952272,
        "tendency": 0
    },
    {
        "key": "如何看待比亚迪在成立 30 周年之际，为回馈新老客户抽 60 台新车使用权，最高奖是仰望 U8？",
        "url": "https://www.zhihu.com/question/1030600684?utm_source=aoyou",
        "count": 901951,
        "tendency": 0
    },
    {
        "key": "我每天工作很快就完成，剩下很多时间在工位上，不知道做什么，大家有没有什么好的建议？",
        "url": "https://www.zhihu.com/question/814888482?utm_source=aoyou",
        "count": 837416,
        "tendency": 0
    },
    {
        "key": "靠严重超常发挥考上北大清华是什么体验？",
        "url": "https://www.zhihu.com/question/803656330?utm_source=aoyou",
        "count": 733554,
        "tendency": 0
    },
    {
        "key": "美国的可回收火箭值得发展吗？机场起降的空天飞机方案是不是更好更安全？",
        "url": "https://www.zhihu.com/question/934564917?utm_source=aoyou",
        "count": 695293,
        "tendency": 0
    },
    {
        "key": "为什么某些中国网民会如此热衷于把所有产业链和资源全部「掌握在自己手里」？",
        "url": "https://www.zhihu.com/question/925810444?utm_source=aoyou",
        "count": 696649,
        "tendency": 0
    },
    {
        "key": "总希望自己以完美的形象出现，发现自己有「失败羞耻」怎么办？",
        "url": "https://www.zhihu.com/question/790905747?utm_source=aoyou",
        "count": 615608,
        "tendency": 0
    }
]