[
    {
        "key": "如何看待 2024 年 8 月本田在中国销量为 56959 辆，同比降幅达到 44.298%？",
        "url": "https://www.zhihu.com/question/666217865?utm_source=aoyou",
        "count": 7271197,
        "tendency": 0
    },
    {
        "key": "黑神话积极修轮椅 bug 却遭吐槽，此次修复为何会遭吐槽？",
        "url": "https://www.zhihu.com/question/665821914?utm_source=aoyou",
        "count": 2710702,
        "tendency": 0
    },
    {
        "key": "如何评价 2024 年数学建模国赛 B 题？",
        "url": "https://www.zhihu.com/question/666299022?utm_source=aoyou",
        "count": 1476033,
        "tendency": 0
    },
    {
        "key": "假如你是米哈游新游策划，且新游不采用米池，你将研发什么新系统赚钱？",
        "url": "https://www.zhihu.com/question/666193292?utm_source=aoyou",
        "count": 1270706,
        "tendency": 0
    },
    {
        "key": "小杨哥一个月掉粉超 70 万，辛巴花 1 亿赔付消费者，这次互撕双方是不是两败俱伤？",
        "url": "https://www.zhihu.com/question/666213085?utm_source=aoyou",
        "count": 1126559,
        "tendency": 0
    },
    {
        "key": "小学一年级孩子做作业拖拉，有什么有效的方法改善？",
        "url": "https://www.zhihu.com/question/665727221?utm_source=aoyou",
        "count": 1073942,
        "tendency": 0
    },
    {
        "key": "为何英国人当年要来中国倾销鸦片？",
        "url": "https://www.zhihu.com/question/627096046?utm_source=aoyou",
        "count": 990107,
        "tendency": 0
    },
    {
        "key": "湘潭教育局通报「家长捐空调」属实，将严肃处理学校，如何评价校方及家长的做法？",
        "url": "https://www.zhihu.com/question/666257714?utm_source=aoyou",
        "count": 873958,
        "tendency": 0
    },
    {
        "key": "为什么越是岁数大，越难心动，对爱越难动心？",
        "url": "https://www.zhihu.com/question/666278535?utm_source=aoyou",
        "count": 516169,
        "tendency": 0
    },
    {
        "key": "《西游记》中黄眉怪为何如此厉害？",
        "url": "https://www.zhihu.com/question/26447750?utm_source=aoyou",
        "count": 402894,
        "tendency": 0
    },
    {
        "key": "国足 0-7 日本赛后曝出多名国脚大骂主教练伊万是「江湖骗子」，如何评价伊万的执教水平?",
        "url": "https://www.zhihu.com/question/666346334?utm_source=aoyou",
        "count": 350279,
        "tendency": 0
    },
    {
        "key": "如何评价刘涛这名演员？",
        "url": "https://www.zhihu.com/question/31194986?utm_source=aoyou",
        "count": 306907,
        "tendency": 0
    },
    {
        "key": "国足 0-7 惨败日本，澳 0-1 负巴林，沙印战平，C 组陷入群雄混战，中国能否混水摸鱼捞到一个出线名额?",
        "url": "https://www.zhihu.com/question/666331480?utm_source=aoyou",
        "count": 271871,
        "tendency": 0
    },
    {
        "key": "四川曾到处是老虎，大熊猫为何没有被吃绝？",
        "url": "https://www.zhihu.com/question/628124546?utm_source=aoyou",
        "count": 256137,
        "tendency": 0
    },
    {
        "key": "据说家猪放生会一年内野化成有獠牙的野猪，这是什么原理？",
        "url": "https://www.zhihu.com/question/362529810?utm_source=aoyou",
        "count": 238652,
        "tendency": 0
    },
    {
        "key": "俄外长称美方必须明白不能拿俄方「红线」开玩笑，俄罗斯外长所说的「红线」具体指什么？",
        "url": "https://www.zhihu.com/question/666286235?utm_source=aoyou",
        "count": 234544,
        "tendency": 0
    },
    {
        "key": "资深球迷桂二牛因病去世，曾因国足球赛落败，怒砸电视还跳进长江，这是一种什么样的足球情怀？",
        "url": "https://www.zhihu.com/question/666376383?utm_source=aoyou",
        "count": 198245,
        "tendency": 0
    },
    {
        "key": "如何理解撒贝宁在央视《开讲啦》说哈工大是「国防七子」之首？",
        "url": "https://www.zhihu.com/question/666108181?utm_source=aoyou",
        "count": 140220,
        "tendency": 0
    },
    {
        "key": "如果你的领导老是抢你的功劳，你该怎么办？",
        "url": "https://www.zhihu.com/question/665791592?utm_source=aoyou",
        "count": 0,
        "tendency": 0
    },
    {
        "key": "为什么大家认为上了 985 的孩子了不起？",
        "url": "https://www.zhihu.com/question/654939134?utm_source=aoyou",
        "count": 0,
        "tendency": 0
    }
]